django_solar/__init__.py
django_solar/abstract.py
django_solar/admin.py
django_solar/context.py
django_solar/models.py
django_solar/management/__init__.py
django_solar/management/commands/__init__.py
django_solar/management/commands/solar.py
django_solar/migrations/0001_initial.py
django_solar/migrations/__init__.py
tests/__init__.py
tests/manager.py
tests/management/__init__.py
tests/management/commands/__init__.py
tests/management/commands/init.py
django_solar-0.0.5.dist-info/LICENSE
django_solar-0.0.5.dist-info/METADATA
django_solar-0.0.5.dist-info/WHEEL
django_solar-0.0.5.dist-info/top_level.txt
django_solar-0.0.5.dist-info/RECORD
